pyrinnaitouch/__init__.py
pyrinnaitouch/commands.py
pyrinnaitouch/const.py
pyrinnaitouch/cooler.py
pyrinnaitouch/evap.py
pyrinnaitouch/event.py
pyrinnaitouch/heater.py
pyrinnaitouch/pollconnection.py
pyrinnaitouch/system.py
pyrinnaitouch/system_status.py
pyrinnaitouch/unit_status.py
pyrinnaitouch/util.py
pyrinnaitouch/zone.py
pyrinnaitouch-0.13.1.dist-info/licenses/LICENSE
pyrinnaitouch-0.13.1.dist-info/METADATA
pyrinnaitouch-0.13.1.dist-info/WHEEL
pyrinnaitouch-0.13.1.dist-info/top_level.txt
pyrinnaitouch-0.13.1.dist-info/RECORD
