Metadata-Version: 2.4
Name: pyrinnaitouch
Version: 0.13.1
Summary: A python interface to the Rinnai Touch Wifi controller
Home-page: https://github.com/funtastix/pyrinnaitouch
Download-URL: https://github.com/funtastix/pyrinnaitouch/archive/refs/tags/v0.13.1.tar.gz
Author: Funtastix
License: mit
Keywords: Rinnai Touch,Brivis,IoT
Classifier: Development Status :: 4 - Beta
Classifier: Intended Audience :: Developers
Classifier: Topic :: Home Automation
Classifier: Topic :: System :: Hardware
Classifier: Operating System :: OS Independent
Classifier: License :: OSI Approved :: MIT License
Classifier: Programming Language :: Python :: 3.7
Classifier: Programming Language :: Python :: 3.8
Requires-Python: >=3.9
License-File: LICENSE
Requires-Dist: asyncio
Requires-Dist: async_timeout
Dynamic: author
Dynamic: classifier
Dynamic: description
Dynamic: description-content-type
Dynamic: download-url
Dynamic: home-page
Dynamic: keywords
Dynamic: license
Dynamic: license-file
Dynamic: requires-dist
Dynamic: requires-python
Dynamic: summary
